pgxp/__init__.py
pgxp-0.1.0.dist-info/METADATA
pgxp-0.1.0.dist-info/WHEEL
pgxp-0.1.0.dist-info/RECORD
