Metadata-Version: 2.1
Name: pgxp
Version: 0.1.0
Summary: PostgresSQL X in python
License: MIT
Author: Ali Tavallaie
Author-email: a.tavallaie@gmail.com
Requires-Python: >=3.10,<4.0
Classifier: License :: OSI Approved :: MIT License
Classifier: Programming Language :: Python :: 3
Classifier: Programming Language :: Python :: 3.10
Classifier: Programming Language :: Python :: 3.11
Classifier: Programming Language :: Python :: 3.12
